cows/__init__.py
cows/_filament.c
cows/_filament.cpython-39-darwin.so
cows/_filament.pyx
cows/_skeletonize_3d_cy.cpp
cows/_skeletonize_3d_cy.cpython-39-darwin.so
cows/_skeletonize_3d_cy.pyx
cows/arraycrop.py
cows/catalogue.py
cows/dtype.py
cows/filament.py
cows/skeletonize.py
pycows-0.0.2.dist-info/LICENSE.txt
pycows-0.0.2.dist-info/METADATA
pycows-0.0.2.dist-info/WHEEL
pycows-0.0.2.dist-info/top_level.txt
pycows-0.0.2.dist-info/RECORD
