Metadata-Version: 2.1
Name: pycows
Version: 0.0.2
Summary: Cosmic filament finder
Home-page: https://github.com/SimonPfeifer/python-cows
Author: Simon Pfeifer
Author-email: spfeifer@aip.de
License: BSD-3-Clause
Project-URL: Documentation, https://python-cows.readthedocs.io/
Project-URL: Issue Tracker, https://github.com/SimonPfeifer/cows/issues
Classifier: License :: OSI Approved :: BSD License
Classifier: Operating System :: Unix
Classifier: Operating System :: Microsoft :: Windows
Classifier: Programming Language :: Python
Classifier: Programming Language :: Python :: 3
Classifier: Programming Language :: Python :: 3 :: Only
Classifier: Programming Language :: Python :: 3.6
Classifier: Programming Language :: Python :: 3.7
Classifier: Programming Language :: Python :: 3.8
Classifier: Programming Language :: Python :: 3.9
Classifier: Programming Language :: Python :: 3.10
Classifier: Topic :: Utilities
Requires-Python: >=3.6
License-File: LICENSE.txt
